{"cameraMode":{"drawMode":0,"name":"Shaded","section":"Shading Mode"},"sceneLighting":true,"audioPlay":false,"sceneViewState":{"m_AlwaysRefresh":false,"showFog":true,"showSkybox":false,"showFlares":true,"showImageEffects":true,"showParticleSystems":true,"showVisualEffectGraphs":true,"m_FxEnabled":true},"in2DMode":false,"pivot":{"x":-2.0577311515808107,"y":2.401456356048584,"z":-2.1463582515716554},"rotation":{"x":-0.09575400501489639,"y":0.8652729392051697,"z":-0.18133006989955903,"w":-0.4577009677886963},"size":1.1542242765426636,"orthographic":false}